proyecto_core/__init__.py
proyecto_core-0.0.1.dist-info/METADATA
proyecto_core-0.0.1.dist-info/WHEEL
proyecto_core-0.0.1.dist-info/top_level.txt
proyecto_core-0.0.1.dist-info/RECORD
