Metadata-Version: 2.4
Name: proyecto-core
Version: 0.0.1
Summary: Shared utilities and constants for CRISP-DM packages
Author: Angel Castellanos, Alejandro Azurdia, Diego Morales
Requires-Python: >=3.8
Dynamic: author
Dynamic: requires-python
Dynamic: summary
